[
  {
    "name": "Custom Engineered",
    "source": "CARGO_CRATE",
    "icon": "./icons/weapon-frameworks/custom-engineered.png"
  },
  {
    "name": "Danger Dice",
    "source": "CARGO_CRATE",
    "icon": "./icons/weapon-frameworks/danger-dice.png"
  },
  {
    "name": "Fourth Relic",
    "source": "CARGO_CRATE",
    "icon": "./icons/weapon-frameworks/fourth-relic.png"
  },
  {
    "name": "Glyphid Trophy Hunter",
    "source": "CARGO_CRATE",
    "icon": "./icons/weapon-frameworks/glyphid-trophy-hunter.png"
  },
  {
    "name": "Mechanized",
    "source": "CARGO_CRATE",
    "icon": "./icons/weapon-frameworks/mechanized.png"
  },
  {
    "name": "Neonband",
    "source": "CARGO_CRATE",
    "icon": "./icons/weapon-frameworks/neon-band.png"
  },
  {
    "name": "Scale Brigade",
    "source": "CARGO_CRATE",
    "icon": "./icons/weapon-frameworks/scale-brigade.png"
  },
  {
    "name": "Waster",
    "source": "PERFORMANCE_PASS",
    "icon": "./icons/weapon-frameworks/waster.png"
  },
  {
    "name": "Builder's Choice",
    "source": "PERFORMANCE_PASS",
    "icon": "./icons/weapon-frameworks/builders-choice.png"
  },
  {
    "name": "MilSpec",
    "source": "PERFORMANCE_PASS",
    "icon": "./icons/weapon-frameworks/mil-spec.png"
  },
  {
    "name": "Infected",
    "source": "PERFORMANCE_PASS",
    "icon": "./icons/weapon-frameworks/infected.png"
  },
  {
    "name": "NEO-TEKYA",
    "source": "PERFORMANCE_PASS",
    "icon": "./icons/weapon-frameworks/neo-tekya.png"
  }
]
